wultiplexor-0.1.0.dist-info/METADATA
wultiplexor-0.1.0.dist-info/WHEEL
wultiplexor-0.1.0.dist-info/entry_points.txt
wultiplexor-0.1.0.dist-info/licenses/LICENSE
wultiplexor/__init__.py
wultiplexor/version.py
wultiplexor/whannel.py
wultiplexor/wultiplexor.py
wultiplexor-0.1.0.dist-info/RECORD
