Metadata-Version: 2.1
Name: wultiplexor
Version: 0.1.0
Summary: This tool is for forwarding TCP or SOCK connections from one computer to another using a central web socket server.
Keywords: proxy gate gateway websocket network networking websockets tcp socks forward forwarding tunnel tunneling tunnelling multiplex multiplexing multiplexer
Home-page: https://github.com/vd2org/wultiplexor
Author-Email: Vd <wultiplexor@vd2.org>
License: Copyright 2024 Vd <wultiplexor@vd2.org>
Classifier: Development Status :: 4 - Beta
Classifier: Intended Audience :: Developers
Classifier: Intended Audience :: End Users/Desktop
Classifier: Intended Audience :: Information Technology
Classifier: Intended Audience :: System Administrators
Classifier: Topic :: Internet :: Proxy Servers
Classifier: Topic :: System :: Networking
Classifier: License :: OSI Approved :: MIT License
Classifier: Programming Language :: Python :: 3
Classifier: Programming Language :: Python :: 3.8
Classifier: Programming Language :: Python :: 3.9
Classifier: Programming Language :: Python :: 3.10
Classifier: Programming Language :: Python :: 3.11
Classifier: Programming Language :: Python :: 3.12
Project-URL: Homepage, https://github.com/vd2org/wultiplexor
Project-URL: Repository, https://github.com/vd2org/wultiplexor.git
Project-URL: Issues, https://github.com/vd2org/wultiplexor/issues
Requires-Python: <3.13,>=3.8
Requires-Dist: websockets~=12.0
